humsana/__init__.py
humsana/activity_tracker.py
humsana/analyzer.py
humsana/audit.py
humsana/auth.py
humsana/cli.py
humsana/collector.py
humsana/config.py
humsana/interlock.py
humsana/local_db.py
humsana/notifications.py
humsana_daemon-2.1.0.dist-info/METADATA
humsana_daemon-2.1.0.dist-info/WHEEL
humsana_daemon-2.1.0.dist-info/entry_points.txt
humsana_daemon-2.1.0.dist-info/top_level.txt
humsana_daemon-2.1.0.dist-info/RECORD
