Metadata-Version: 2.1
Name: humsana-daemon
Version: 2.1.0
Summary: Local behavioral signal collection for Humsana Cognitive Security
Home-page: https://github.com/sriramnatrajhen/humsana-daemon
Author: Humsana
Author-email: ram.natrajhen@gmail.com
Classifier: Programming Language :: Python :: 3
Classifier: License :: OSI Approved :: MIT License
Classifier: Operating System :: OS Independent
Requires-Python: >=3.8
Requires-Dist: pynput>=1.7.6
Requires-Dist: PyYAML>=6.0
Requires-Dist: requests>=2.28.0
